agn/__init__.py
agn/cli.py
agn/agents/base.py
agn/agents/runner.py
agn/agents/simple_openai_agent.py
agn/core/__init__.py
agn/core/base_protocol.py
agn/core/base_protocol_adapter.py
agn/core/client.py
agn/core/connector.py
agn/core/network.py
agn/core/system_commands.py
agn/launchers/__init__.py
agn/launchers/discovery_connector.py
agn/launchers/network_launcher.py
agn/launchers/terminal_console.py
agn/models/__init__.py
agn/models/manifest.py
agn/models/message_thread.py
agn/models/messages.py
agn/models/network_config.py
agn/models/network_profile.py
agn/models/tool.py
agn/protocols/__init__.py
agn/protocols/communication/__init__.py
agn/protocols/communication/simple_messaging/__init__.py
agn/protocols/communication/simple_messaging/adapter.py
agn/protocols/communication/simple_messaging/protocol.py
agn/protocols/discovery/__init__.py
agn/protocols/discovery/agent_discovery/__init__.py
agn/protocols/discovery/agent_discovery/adapter.py
agn/protocols/discovery/agent_discovery/protocol.py
agn/utils/__init__.py
agn/utils/message_util.py
agn/utils/network_discovey.py
agn/utils/protocol_loaders.py
agn-0.4.0.dist-info/licenses/LICENSE
omniagents/__init__.py
openagents/__init__.py
openagents/cli.py
openagents/agents/base.py
openagents/agents/runner.py
openagents/agents/simple_openai_agent.py
openagents/core/__init__.py
openagents/core/base_protocol.py
openagents/core/base_protocol_adapter.py
openagents/core/client.py
openagents/core/connector.py
openagents/core/network.py
openagents/core/system_commands.py
openagents/launchers/__init__.py
openagents/launchers/discovery_connector.py
openagents/launchers/network_launcher.py
openagents/launchers/terminal_console.py
openagents/models/__init__.py
openagents/models/manifest.py
openagents/models/message_thread.py
openagents/models/messages.py
openagents/models/network_config.py
openagents/models/network_profile.py
openagents/models/tool.py
openagents/protocols/__init__.py
openagents/protocols/communication/__init__.py
agn-0.4.0.dist-info/METADATA
agn-0.4.0.dist-info/WHEEL
agn-0.4.0.dist-info/entry_points.txt
agn-0.4.0.dist-info/top_level.txt
agn-0.4.0.dist-info/RECORD
